nc_dnsapi/__init__.py
nc_dnsapi-0.1.5.dist-info/METADATA
nc_dnsapi-0.1.5.dist-info/RECORD
nc_dnsapi-0.1.5.dist-info/WHEEL
nc_dnsapi-0.1.5.dist-info/top_level.txt
