Metadata-Version: 2.1
Name: nc-dnsapi
Version: 0.1.5
Summary: API wrapper for the netcup DNS api
Home-page: https://github.com/nbuchwitz/nc_dnsapi
Author: Nicolai Buchwitz
Author-email: nb@tipi-net.de
License: UNKNOWN
Platform: UNKNOWN
Classifier: Programming Language :: Python :: 3
Classifier: Programming Language :: Python :: 2.7
Classifier: License :: OSI Approved :: GNU General Public License v3 (GPLv3)
Classifier: Operating System :: OS Independent
Requires-Dist: requests
